ier_processor/__init__.py
ier_processor/__main__.py
ier_processor/image_record_processing.py
ier_processor/pdf_slicing.py
ier_processor/spark_job.py
ier_processor/spark_job_emr.py
ier_processor/spark_job_local.py
ier_processor/utils.py
ier_processor/test_data/whole_pdf/Benaulim/Part01.pdf
indian_electoral_roll_processor-1.0.15.dist-info/METADATA
indian_electoral_roll_processor-1.0.15.dist-info/WHEEL
indian_electoral_roll_processor-1.0.15.dist-info/top_level.txt
indian_electoral_roll_processor-1.0.15.dist-info/RECORD
