Metadata-Version: 2.1
Name: indian-electoral-roll-processor
Version: 1.0.15
Summary: UNKNOWN
Home-page: UNKNOWN
Author: UNKNOWN
Author-email: UNKNOWN
License: MIT
Platform: UNKNOWN
Classifier: License :: OSI Approved :: MIT License
Classifier: Programming Language :: Python :: 3
Classifier: Programming Language :: Python :: 3.7
Requires-Dist: asgiref (==3.2.7)
Requires-Dist: boto3 (==1.14.26)
Requires-Dist: botocore (==1.17.27)
Requires-Dist: chardet (==3.0.4)
Requires-Dist: docutils (==0.15.2)
Requires-Dist: jmespath (==0.10.0)
Requires-Dist: pdf2image (==1.13.1)
Requires-Dist: Pillow (==7.1.1)
Requires-Dist: pyasn1 (==0.4.8)
Requires-Dist: pycryptodome (==3.9.7)
Requires-Dist: pytesseract (==0.3.3)
Requires-Dist: python-dateutil (==2.8.1)
Requires-Dist: pytz (==2019.3)
Requires-Dist: PyYAML (==5.3.1)
Requires-Dist: rsa (==4.5)
Requires-Dist: s3transfer (==0.3.3)
Requires-Dist: six (==1.14.0)
Requires-Dist: urllib3 (==1.25.10)
